fermata_cli/__init__.py
fermata_cli/completor.py
fermata_cli/debugger.py
fermata_cli/initializer.py
fermata_cli/util.py
fermata_cli-0.0.4.dist-info/METADATA
fermata_cli-0.0.4.dist-info/WHEEL
fermata_cli-0.0.4.dist-info/entry_points.txt
fermata_cli-0.0.4.dist-info/top_level.txt
fermata_cli-0.0.4.dist-info/RECORD
