Metadata-Version: 2.1
Name: fermata-cli
Version: 0.0.4
Summary: Command Line Interface of Fermata
Home-page: https://fenda.io/ff/fermata-cli
Author: rejown
Author-email: rejown@gmail.com
License: UNKNOWN
Platform: UNKNOWN
Requires-Python: >=3.6
Requires-Dist: fermata
Requires-Dist: docopt
Requires-Dist: werkzeug
Requires-Dist: meinheld
Requires-Dist: pyyaml
Requires-Dist: coloredlogs
